<problemDefinition>
  <nPartTypes>4</nPartTypes>
  <nParts>114</nParts>
  <meanDemand>28.5</meanDemand>
  <rsdDemand>0.2141500985216439</rsdDemand>
  <meanMCV>0.5316324561403509</meanMCV>
  <rsdMCV>0.42600678553862237</rsdMCV>
  <meanSR>0.21874649122807047</meanSR>
  <rsdSR>1.090848202030925</rsdSR>
  <meanVolMBB>1342246.9698561388</meanVolMBB>
  <rsdVolMBB>0.85390726052355</rsdVolMBB>
  <meanNumFacets>6557.929824561404</meanNumFacets>
  <rsdNumFacets>1.6292452532713757</rsdNumFacets>
  <meanSurfaceArea>58057.44335526313</meanSurfaceArea>
  <rsdSurfaceArea>0.4694902929712456</rsdSurfaceArea>
  <meanVolume>86817.95152543853</meanVolume>
  <rsdVolume>0.5748358327945057</rsdVolume>
  <containers>
    <cuboid id="0">
      <height>250.0</height>
      <volume>1.875E7</volume>
      <cost>70.5</cost>
      <time>70</time>
      <width>250.0</width>
      <depth>300.0</depth>
    </cuboid>
  </containers>
  <partTypes>
    <partType id="340">
      <demand>28</demand>
      <mcv>0.4048</mcv>
      <vValue>0.1114</vValue>
      <sr>0.0308</sr>
      <volMBB>3149144.495</volMBB>
      <facets>25280.0</facets>
      <surfaceArea>104553.1194</surfaceArea>
      <volume>96896.5032</volume>
    </partType>
    <partType id="279">
      <demand>27</demand>
      <mcv>0.2237</mcv>
      <vValue>0.0793</vValue>
      <sr>0.3695</sr>
      <volMBB>206861.3174</volMBB>
      <facets>224.0</facets>
      <surfaceArea>36437.758</surfaceArea>
      <volume>76426.5157</volume>
    </partType>
    <partType id="253">
      <demand>21</demand>
      <mcv>0.6152</mcv>
      <vValue>0.1175</vValue>
      <sr>0.6252</sr>
      <volMBB>286538.2298</volMBB>
      <facets>328.0</facets>
      <surfaceArea>36610.2195</surfaceArea>
      <volume>179156.2124</volume>
    </partType>
    <partType id="430">
      <demand>38</demand>
      <mcv>0.7977</mcv>
      <vValue>0.1015</vValue>
      <sr>0.0255</sr>
      <volMBB>1400988.166</volMBB>
      <facets>706.0</facets>
      <surfaceArea>51011.2401</surfaceArea>
      <volume>35746.0</volume>
    </partType>
  </partTypes>
  <parts>
    <part id="340:0">
      <idPartType>340</idPartType>
      <value>64.75</value>
      <dueDate>54</dueDate>
    </part>
    <part id="340:1">
      <idPartType>340</idPartType>
      <value>17.09</value>
      <dueDate>32</dueDate>
    </part>
    <part id="340:2">
      <idPartType>340</idPartType>
      <value>69.63</value>
      <dueDate>42</dueDate>
    </part>
    <part id="340:3">
      <idPartType>340</idPartType>
      <value>42.14</value>
      <dueDate>34</dueDate>
    </part>
    <part id="340:4">
      <idPartType>340</idPartType>
      <value>45.06</value>
      <dueDate>40</dueDate>
    </part>
    <part id="340:5">
      <idPartType>340</idPartType>
      <value>92.11</value>
      <dueDate>11</dueDate>
    </part>
    <part id="340:6">
      <idPartType>340</idPartType>
      <value>100.84</value>
      <dueDate>69</dueDate>
    </part>
    <part id="340:7">
      <idPartType>340</idPartType>
      <value>60.66</value>
      <dueDate>64</dueDate>
    </part>
    <part id="340:8">
      <idPartType>340</idPartType>
      <value>1.78</value>
      <dueDate>66</dueDate>
    </part>
    <part id="340:9">
      <idPartType>340</idPartType>
      <value>2.86</value>
      <dueDate>38</dueDate>
    </part>
    <part id="340:10">
      <idPartType>340</idPartType>
      <value>19.34</value>
      <dueDate>33</dueDate>
    </part>
    <part id="340:11">
      <idPartType>340</idPartType>
      <value>49.81</value>
      <dueDate>26</dueDate>
    </part>
    <part id="340:12">
      <idPartType>340</idPartType>
      <value>44.08</value>
      <dueDate>6</dueDate>
    </part>
    <part id="340:13">
      <idPartType>340</idPartType>
      <value>93.92</value>
      <dueDate>50</dueDate>
    </part>
    <part id="340:14">
      <idPartType>340</idPartType>
      <value>97.9</value>
      <dueDate>63</dueDate>
    </part>
    <part id="340:15">
      <idPartType>340</idPartType>
      <value>48.71</value>
      <dueDate>57</dueDate>
    </part>
    <part id="340:16">
      <idPartType>340</idPartType>
      <value>6.46</value>
      <dueDate>30</dueDate>
    </part>
    <part id="340:17">
      <idPartType>340</idPartType>
      <value>1.11</value>
      <dueDate>59</dueDate>
    </part>
    <part id="340:18">
      <idPartType>340</idPartType>
      <value>84.39</value>
      <dueDate>25</dueDate>
    </part>
    <part id="340:19">
      <idPartType>340</idPartType>
      <value>61.54</value>
      <dueDate>7</dueDate>
    </part>
    <part id="340:20">
      <idPartType>340</idPartType>
      <value>78.99</value>
      <dueDate>23</dueDate>
    </part>
    <part id="340:21">
      <idPartType>340</idPartType>
      <value>75.63</value>
      <dueDate>31</dueDate>
    </part>
    <part id="340:22">
      <idPartType>340</idPartType>
      <value>69.93</value>
      <dueDate>44</dueDate>
    </part>
    <part id="340:23">
      <idPartType>340</idPartType>
      <value>59.03</value>
      <dueDate>35</dueDate>
    </part>
    <part id="340:24">
      <idPartType>340</idPartType>
      <value>81.33</value>
      <dueDate>44</dueDate>
    </part>
    <part id="340:25">
      <idPartType>340</idPartType>
      <value>41.01</value>
      <dueDate>7</dueDate>
    </part>
    <part id="340:26">
      <idPartType>340</idPartType>
      <value>68.23</value>
      <dueDate>65</dueDate>
    </part>
    <part id="340:27">
      <idPartType>340</idPartType>
      <value>86.05</value>
      <dueDate>46</dueDate>
    </part>
    <part id="279:0">
      <idPartType>279</idPartType>
      <value>8.84</value>
      <dueDate>10</dueDate>
    </part>
    <part id="279:1">
      <idPartType>279</idPartType>
      <value>63.18</value>
      <dueDate>31</dueDate>
    </part>
    <part id="279:2">
      <idPartType>279</idPartType>
      <value>76.03</value>
      <dueDate>24</dueDate>
    </part>
    <part id="279:3">
      <idPartType>279</idPartType>
      <value>38.17</value>
      <dueDate>3</dueDate>
    </part>
    <part id="279:4">
      <idPartType>279</idPartType>
      <value>96.66</value>
      <dueDate>24</dueDate>
    </part>
    <part id="279:5">
      <idPartType>279</idPartType>
      <value>17.7</value>
      <dueDate>40</dueDate>
    </part>
    <part id="279:6">
      <idPartType>279</idPartType>
      <value>34.52</value>
      <dueDate>10</dueDate>
    </part>
    <part id="279:7">
      <idPartType>279</idPartType>
      <value>61.15</value>
      <dueDate>29</dueDate>
    </part>
    <part id="279:8">
      <idPartType>279</idPartType>
      <value>69.64</value>
      <dueDate>18</dueDate>
    </part>
    <part id="279:9">
      <idPartType>279</idPartType>
      <value>82.4</value>
      <dueDate>26</dueDate>
    </part>
    <part id="279:10">
      <idPartType>279</idPartType>
      <value>71.84</value>
      <dueDate>67</dueDate>
    </part>
    <part id="279:11">
      <idPartType>279</idPartType>
      <value>20.99</value>
      <dueDate>40</dueDate>
    </part>
    <part id="279:12">
      <idPartType>279</idPartType>
      <value>31.66</value>
      <dueDate>12</dueDate>
    </part>
    <part id="279:13">
      <idPartType>279</idPartType>
      <value>4.21</value>
      <dueDate>64</dueDate>
    </part>
    <part id="279:14">
      <idPartType>279</idPartType>
      <value>58.09</value>
      <dueDate>10</dueDate>
    </part>
    <part id="279:15">
      <idPartType>279</idPartType>
      <value>39.65</value>
      <dueDate>11</dueDate>
    </part>
    <part id="279:16">
      <idPartType>279</idPartType>
      <value>30.37</value>
      <dueDate>34</dueDate>
    </part>
    <part id="279:17">
      <idPartType>279</idPartType>
      <value>13.11</value>
      <dueDate>33</dueDate>
    </part>
    <part id="279:18">
      <idPartType>279</idPartType>
      <value>14.92</value>
      <dueDate>60</dueDate>
    </part>
    <part id="279:19">
      <idPartType>279</idPartType>
      <value>2.96</value>
      <dueDate>39</dueDate>
    </part>
    <part id="279:20">
      <idPartType>279</idPartType>
      <value>44.76</value>
      <dueDate>5</dueDate>
    </part>
    <part id="279:21">
      <idPartType>279</idPartType>
      <value>28.17</value>
      <dueDate>11</dueDate>
    </part>
    <part id="279:22">
      <idPartType>279</idPartType>
      <value>67.67</value>
      <dueDate>57</dueDate>
    </part>
    <part id="279:23">
      <idPartType>279</idPartType>
      <value>7.65</value>
      <dueDate>24</dueDate>
    </part>
    <part id="279:24">
      <idPartType>279</idPartType>
      <value>38.3</value>
      <dueDate>46</dueDate>
    </part>
    <part id="279:25">
      <idPartType>279</idPartType>
      <value>7.74</value>
      <dueDate>35</dueDate>
    </part>
    <part id="279:26">
      <idPartType>279</idPartType>
      <value>24.51</value>
      <dueDate>23</dueDate>
    </part>
    <part id="253:0">
      <idPartType>253</idPartType>
      <value>18.94</value>
      <dueDate>24</dueDate>
    </part>
    <part id="253:1">
      <idPartType>253</idPartType>
      <value>3.14</value>
      <dueDate>66</dueDate>
    </part>
    <part id="253:2">
      <idPartType>253</idPartType>
      <value>92.29</value>
      <dueDate>25</dueDate>
    </part>
    <part id="253:3">
      <idPartType>253</idPartType>
      <value>88.07</value>
      <dueDate>13</dueDate>
    </part>
    <part id="253:4">
      <idPartType>253</idPartType>
      <value>78.0</value>
      <dueDate>24</dueDate>
    </part>
    <part id="253:5">
      <idPartType>253</idPartType>
      <value>68.37</value>
      <dueDate>38</dueDate>
    </part>
    <part id="253:6">
      <idPartType>253</idPartType>
      <value>19.4</value>
      <dueDate>14</dueDate>
    </part>
    <part id="253:7">
      <idPartType>253</idPartType>
      <value>11.3</value>
      <dueDate>3</dueDate>
    </part>
    <part id="253:8">
      <idPartType>253</idPartType>
      <value>8.54</value>
      <dueDate>38</dueDate>
    </part>
    <part id="253:9">
      <idPartType>253</idPartType>
      <value>32.66</value>
      <dueDate>51</dueDate>
    </part>
    <part id="253:10">
      <idPartType>253</idPartType>
      <value>20.38</value>
      <dueDate>39</dueDate>
    </part>
    <part id="253:11">
      <idPartType>253</idPartType>
      <value>72.76</value>
      <dueDate>30</dueDate>
    </part>
    <part id="253:12">
      <idPartType>253</idPartType>
      <value>79.05</value>
      <dueDate>44</dueDate>
    </part>
    <part id="253:13">
      <idPartType>253</idPartType>
      <value>8.41</value>
      <dueDate>24</dueDate>
    </part>
    <part id="253:14">
      <idPartType>253</idPartType>
      <value>42.13</value>
      <dueDate>54</dueDate>
    </part>
    <part id="253:15">
      <idPartType>253</idPartType>
      <value>74.1</value>
      <dueDate>18</dueDate>
    </part>
    <part id="253:16">
      <idPartType>253</idPartType>
      <value>43.09</value>
      <dueDate>39</dueDate>
    </part>
    <part id="253:17">
      <idPartType>253</idPartType>
      <value>77.07</value>
      <dueDate>19</dueDate>
    </part>
    <part id="253:18">
      <idPartType>253</idPartType>
      <value>48.47</value>
      <dueDate>40</dueDate>
    </part>
    <part id="253:19">
      <idPartType>253</idPartType>
      <value>23.17</value>
      <dueDate>56</dueDate>
    </part>
    <part id="253:20">
      <idPartType>253</idPartType>
      <value>95.6</value>
      <dueDate>34</dueDate>
    </part>
    <part id="430:0">
      <idPartType>430</idPartType>
      <value>75.55</value>
      <dueDate>56</dueDate>
    </part>
    <part id="430:1">
      <idPartType>430</idPartType>
      <value>8.09</value>
      <dueDate>45</dueDate>
    </part>
    <part id="430:2">
      <idPartType>430</idPartType>
      <value>14.34</value>
      <dueDate>66</dueDate>
    </part>
    <part id="430:3">
      <idPartType>430</idPartType>
      <value>93.0</value>
      <dueDate>45</dueDate>
    </part>
    <part id="430:4">
      <idPartType>430</idPartType>
      <value>80.16</value>
      <dueDate>39</dueDate>
    </part>
    <part id="430:5">
      <idPartType>430</idPartType>
      <value>52.64</value>
      <dueDate>7</dueDate>
    </part>
    <part id="430:6">
      <idPartType>430</idPartType>
      <value>17.79</value>
      <dueDate>60</dueDate>
    </part>
    <part id="430:7">
      <idPartType>430</idPartType>
      <value>15.32</value>
      <dueDate>65</dueDate>
    </part>
    <part id="430:8">
      <idPartType>430</idPartType>
      <value>69.81</value>
      <dueDate>11</dueDate>
    </part>
    <part id="430:9">
      <idPartType>430</idPartType>
      <value>13.64</value>
      <dueDate>37</dueDate>
    </part>
    <part id="430:10">
      <idPartType>430</idPartType>
      <value>44.44</value>
      <dueDate>11</dueDate>
    </part>
    <part id="430:11">
      <idPartType>430</idPartType>
      <value>27.89</value>
      <dueDate>40</dueDate>
    </part>
    <part id="430:12">
      <idPartType>430</idPartType>
      <value>26.13</value>
      <dueDate>6</dueDate>
    </part>
    <part id="430:13">
      <idPartType>430</idPartType>
      <value>11.31</value>
      <dueDate>19</dueDate>
    </part>
    <part id="430:14">
      <idPartType>430</idPartType>
      <value>23.37</value>
      <dueDate>4</dueDate>
    </part>
    <part id="430:15">
      <idPartType>430</idPartType>
      <value>89.31</value>
      <dueDate>24</dueDate>
    </part>
    <part id="430:16">
      <idPartType>430</idPartType>
      <value>28.71</value>
      <dueDate>17</dueDate>
    </part>
    <part id="430:17">
      <idPartType>430</idPartType>
      <value>56.66</value>
      <dueDate>16</dueDate>
    </part>
    <part id="430:18">
      <idPartType>430</idPartType>
      <value>63.75</value>
      <dueDate>22</dueDate>
    </part>
    <part id="430:19">
      <idPartType>430</idPartType>
      <value>64.41</value>
      <dueDate>25</dueDate>
    </part>
    <part id="430:20">
      <idPartType>430</idPartType>
      <value>91.72</value>
      <dueDate>3</dueDate>
    </part>
    <part id="430:21">
      <idPartType>430</idPartType>
      <value>40.59</value>
      <dueDate>5</dueDate>
    </part>
    <part id="430:22">
      <idPartType>430</idPartType>
      <value>31.14</value>
      <dueDate>50</dueDate>
    </part>
    <part id="430:23">
      <idPartType>430</idPartType>
      <value>30.36</value>
      <dueDate>2</dueDate>
    </part>
    <part id="430:24">
      <idPartType>430</idPartType>
      <value>50.64</value>
      <dueDate>45</dueDate>
    </part>
    <part id="430:25">
      <idPartType>430</idPartType>
      <value>63.48</value>
      <dueDate>23</dueDate>
    </part>
    <part id="430:26">
      <idPartType>430</idPartType>
      <value>44.85</value>
      <dueDate>24</dueDate>
    </part>
    <part id="430:27">
      <idPartType>430</idPartType>
      <value>8.94</value>
      <dueDate>25</dueDate>
    </part>
    <part id="430:28">
      <idPartType>430</idPartType>
      <value>79.34</value>
      <dueDate>47</dueDate>
    </part>
    <part id="430:29">
      <idPartType>430</idPartType>
      <value>16.49</value>
      <dueDate>15</dueDate>
    </part>
    <part id="430:30">
      <idPartType>430</idPartType>
      <value>53.61</value>
      <dueDate>41</dueDate>
    </part>
    <part id="430:31">
      <idPartType>430</idPartType>
      <value>47.14</value>
      <dueDate>21</dueDate>
    </part>
    <part id="430:32">
      <idPartType>430</idPartType>
      <value>6.36</value>
      <dueDate>51</dueDate>
    </part>
    <part id="430:33">
      <idPartType>430</idPartType>
      <value>63.1</value>
      <dueDate>3</dueDate>
    </part>
    <part id="430:34">
      <idPartType>430</idPartType>
      <value>14.05</value>
      <dueDate>27</dueDate>
    </part>
    <part id="430:35">
      <idPartType>430</idPartType>
      <value>83.87</value>
      <dueDate>33</dueDate>
    </part>
    <part id="430:36">
      <idPartType>430</idPartType>
      <value>12.17</value>
      <dueDate>34</dueDate>
    </part>
    <part id="430:37">
      <idPartType>430</idPartType>
      <value>6.97</value>
      <dueDate>25</dueDate>
    </part>
  </parts>
</problemDefinition>