<problemDefinition>
  <nPartTypes>8</nPartTypes>
  <nParts>288</nParts>
  <meanDemand>36.0</meanDemand>
  <rsdDemand>0.11702985796078276</rsdDemand>
  <meanMCV>0.5186993055555557</meanMCV>
  <rsdMCV>0.44852378224194084</rsdMCV>
  <meanSR>0.18695798611111095</meanSR>
  <rsdSR>0.8073067724276449</rsdSR>
  <meanVolMBB>385727.08059618087</meanVolMBB>
  <rsdVolMBB>0.7223514710824949</rsdVolMBB>
  <meanNumFacets>21921.680555555555</meanNumFacets>
  <rsdNumFacets>0.8854796567658682</rsdNumFacets>
  <meanSurfaceArea>24307.252387499884</meanSurfaceArea>
  <rsdSurfaceArea>0.7089203402669362</rsdSurfaceArea>
  <meanVolume>82824.2896093747</meanVolume>
  <rsdVolume>1.099504304901741</rsdVolume>
  <containers>
    <cuboid id="0">
      <height>252.0</height>
      <volume>1.2852E7</volume>
      <cost>90.2</cost>
      <time>85</time>
      <width>255.0</width>
      <depth>200.0</depth>
    </cuboid>
  </containers>
  <partTypes>
    <partType id="32">
      <demand>35</demand>
      <mcv>0.4835</mcv>
      <vValue>0.0898</vValue>
      <sr>0.1722</sr>
      <volMBB>402867.5281</volMBB>
      <facets>10394.0</facets>
      <surfaceArea>46404.6115</surfaceArea>
      <volume>69356.1664</volume>
    </partType>
    <partType id="308">
      <demand>31</demand>
      <mcv>0.3482</mcv>
      <vValue>0.1934</vValue>
      <sr>0.0427</sr>
      <volMBB>248138.4799</volMBB>
      <facets>41026.0</facets>
      <surfaceArea>12238.0993</surfaceArea>
      <volume>10583.9182</volume>
    </partType>
    <partType id="293">
      <demand>33</demand>
      <mcv>0.7141</mcv>
      <vValue>0.217</vValue>
      <sr>0.1021</sr>
      <volMBB>282556.8014</volMBB>
      <facets>5660.0</facets>
      <surfaceArea>7752.2449</surfaceArea>
      <volume>28860.937</volume>
    </partType>
    <partType id="374">
      <demand>37</demand>
      <mcv>0.8988</mcv>
      <vValue>0.1224</vValue>
      <sr>0.0902</sr>
      <volMBB>339688.5785</volMBB>
      <facets>46034.0</facets>
      <surfaceArea>12613.2323</surfaceArea>
      <volume>30652.3728</volume>
    </partType>
    <partType id="7">
      <demand>45</demand>
      <mcv>0.7496</mcv>
      <vValue>0.1679</vValue>
      <sr>0.4959</sr>
      <volMBB>512000.0</volMBB>
      <facets>110.0</facets>
      <surfaceArea>27530.5588</surfaceArea>
      <volume>253904.6661</volume>
    </partType>
    <partType id="375">
      <demand>36</demand>
      <mcv>0.2902</mcv>
      <vValue>0.1366</vValue>
      <sr>0.0394</sr>
      <volMBB>140958.2903</volMBB>
      <facets>50398.0</facets>
      <surfaceArea>12978.0365</surfaceArea>
      <volume>5553.023</volume>
    </partType>
    <partType id="189">
      <demand>39</demand>
      <mcv>0.3218</mcv>
      <vValue>0.1494</vValue>
      <sr>0.2658</sr>
      <volMBB>117198.9622</volMBB>
      <facets>4748.0</facets>
      <surfaceArea>16142.2468</surfaceArea>
      <volume>31152.5162</volume>
    </partType>
    <partType id="93">
      <demand>32</demand>
      <mcv>0.2537</mcv>
      <vValue>0.0926</vValue>
      <sr>0.1777</sr>
      <volMBB>1084957.282</volMBB>
      <facets>24480.0</facets>
      <surfaceArea>60587.5139</surfaceArea>
      <volume>192834.7647</volume>
    </partType>
  </partTypes>
  <parts>
    <part id="32:0">
      <idPartType>32</idPartType>
      <value>10.04</value>
      <dueDate>70</dueDate>
    </part>
    <part id="32:1">
      <idPartType>32</idPartType>
      <value>7.85</value>
      <dueDate>79</dueDate>
    </part>
    <part id="32:2">
      <idPartType>32</idPartType>
      <value>39.26</value>
      <dueDate>79</dueDate>
    </part>
    <part id="32:3">
      <idPartType>32</idPartType>
      <value>10.24</value>
      <dueDate>76</dueDate>
    </part>
    <part id="32:4">
      <idPartType>32</idPartType>
      <value>36.22</value>
      <dueDate>74</dueDate>
    </part>
    <part id="32:5">
      <idPartType>32</idPartType>
      <value>33.6</value>
      <dueDate>48</dueDate>
    </part>
    <part id="32:6">
      <idPartType>32</idPartType>
      <value>87.31</value>
      <dueDate>64</dueDate>
    </part>
    <part id="32:7">
      <idPartType>32</idPartType>
      <value>26.64</value>
      <dueDate>9</dueDate>
    </part>
    <part id="32:8">
      <idPartType>32</idPartType>
      <value>4.73</value>
      <dueDate>76</dueDate>
    </part>
    <part id="32:9">
      <idPartType>32</idPartType>
      <value>56.26</value>
      <dueDate>6</dueDate>
    </part>
    <part id="32:10">
      <idPartType>32</idPartType>
      <value>81.79</value>
      <dueDate>60</dueDate>
    </part>
    <part id="32:11">
      <idPartType>32</idPartType>
      <value>30.28</value>
      <dueDate>19</dueDate>
    </part>
    <part id="32:12">
      <idPartType>32</idPartType>
      <value>1.52</value>
      <dueDate>57</dueDate>
    </part>
    <part id="32:13">
      <idPartType>32</idPartType>
      <value>60.78</value>
      <dueDate>69</dueDate>
    </part>
    <part id="32:14">
      <idPartType>32</idPartType>
      <value>12.71</value>
      <dueDate>58</dueDate>
    </part>
    <part id="32:15">
      <idPartType>32</idPartType>
      <value>50.31</value>
      <dueDate>74</dueDate>
    </part>
    <part id="32:16">
      <idPartType>32</idPartType>
      <value>52.21</value>
      <dueDate>15</dueDate>
    </part>
    <part id="32:17">
      <idPartType>32</idPartType>
      <value>39.43</value>
      <dueDate>63</dueDate>
    </part>
    <part id="32:18">
      <idPartType>32</idPartType>
      <value>43.0</value>
      <dueDate>65</dueDate>
    </part>
    <part id="32:19">
      <idPartType>32</idPartType>
      <value>89.23</value>
      <dueDate>51</dueDate>
    </part>
    <part id="32:20">
      <idPartType>32</idPartType>
      <value>39.81</value>
      <dueDate>46</dueDate>
    </part>
    <part id="32:21">
      <idPartType>32</idPartType>
      <value>63.02</value>
      <dueDate>13</dueDate>
    </part>
    <part id="32:22">
      <idPartType>32</idPartType>
      <value>73.49</value>
      <dueDate>45</dueDate>
    </part>
    <part id="32:23">
      <idPartType>32</idPartType>
      <value>54.07</value>
      <dueDate>40</dueDate>
    </part>
    <part id="32:24">
      <idPartType>32</idPartType>
      <value>60.42</value>
      <dueDate>41</dueDate>
    </part>
    <part id="32:25">
      <idPartType>32</idPartType>
      <value>54.68</value>
      <dueDate>11</dueDate>
    </part>
    <part id="32:26">
      <idPartType>32</idPartType>
      <value>5.35</value>
      <dueDate>67</dueDate>
    </part>
    <part id="32:27">
      <idPartType>32</idPartType>
      <value>97.29</value>
      <dueDate>85</dueDate>
    </part>
    <part id="32:28">
      <idPartType>32</idPartType>
      <value>18.44</value>
      <dueDate>10</dueDate>
    </part>
    <part id="32:29">
      <idPartType>32</idPartType>
      <value>82.09</value>
      <dueDate>39</dueDate>
    </part>
    <part id="32:30">
      <idPartType>32</idPartType>
      <value>86.68</value>
      <dueDate>66</dueDate>
    </part>
    <part id="32:31">
      <idPartType>32</idPartType>
      <value>56.64</value>
      <dueDate>10</dueDate>
    </part>
    <part id="32:32">
      <idPartType>32</idPartType>
      <value>58.3</value>
      <dueDate>66</dueDate>
    </part>
    <part id="32:33">
      <idPartType>32</idPartType>
      <value>44.93</value>
      <dueDate>82</dueDate>
    </part>
    <part id="32:34">
      <idPartType>32</idPartType>
      <value>24.64</value>
      <dueDate>11</dueDate>
    </part>
    <part id="308:0">
      <idPartType>308</idPartType>
      <value>43.27</value>
      <dueDate>36</dueDate>
    </part>
    <part id="308:1">
      <idPartType>308</idPartType>
      <value>49.05</value>
      <dueDate>24</dueDate>
    </part>
    <part id="308:2">
      <idPartType>308</idPartType>
      <value>95.73</value>
      <dueDate>35</dueDate>
    </part>
    <part id="308:3">
      <idPartType>308</idPartType>
      <value>54.56</value>
      <dueDate>66</dueDate>
    </part>
    <part id="308:4">
      <idPartType>308</idPartType>
      <value>26.46</value>
      <dueDate>32</dueDate>
    </part>
    <part id="308:5">
      <idPartType>308</idPartType>
      <value>32.74</value>
      <dueDate>61</dueDate>
    </part>
    <part id="308:6">
      <idPartType>308</idPartType>
      <value>60.41</value>
      <dueDate>69</dueDate>
    </part>
    <part id="308:7">
      <idPartType>308</idPartType>
      <value>33.15</value>
      <dueDate>20</dueDate>
    </part>
    <part id="308:8">
      <idPartType>308</idPartType>
      <value>26.25</value>
      <dueDate>35</dueDate>
    </part>
    <part id="308:9">
      <idPartType>308</idPartType>
      <value>70.68</value>
      <dueDate>24</dueDate>
    </part>
    <part id="308:10">
      <idPartType>308</idPartType>
      <value>37.34</value>
      <dueDate>3</dueDate>
    </part>
    <part id="308:11">
      <idPartType>308</idPartType>
      <value>81.04</value>
      <dueDate>5</dueDate>
    </part>
    <part id="308:12">
      <idPartType>308</idPartType>
      <value>41.68</value>
      <dueDate>11</dueDate>
    </part>
    <part id="308:13">
      <idPartType>308</idPartType>
      <value>59.18</value>
      <dueDate>81</dueDate>
    </part>
    <part id="308:14">
      <idPartType>308</idPartType>
      <value>38.78</value>
      <dueDate>14</dueDate>
    </part>
    <part id="308:15">
      <idPartType>308</idPartType>
      <value>47.65</value>
      <dueDate>77</dueDate>
    </part>
    <part id="308:16">
      <idPartType>308</idPartType>
      <value>82.23</value>
      <dueDate>16</dueDate>
    </part>
    <part id="308:17">
      <idPartType>308</idPartType>
      <value>77.13</value>
      <dueDate>40</dueDate>
    </part>
    <part id="308:18">
      <idPartType>308</idPartType>
      <value>85.37</value>
      <dueDate>62</dueDate>
    </part>
    <part id="308:19">
      <idPartType>308</idPartType>
      <value>36.91</value>
      <dueDate>40</dueDate>
    </part>
    <part id="308:20">
      <idPartType>308</idPartType>
      <value>20.98</value>
      <dueDate>75</dueDate>
    </part>
    <part id="308:21">
      <idPartType>308</idPartType>
      <value>89.31</value>
      <dueDate>20</dueDate>
    </part>
    <part id="308:22">
      <idPartType>308</idPartType>
      <value>83.3</value>
      <dueDate>58</dueDate>
    </part>
    <part id="308:23">
      <idPartType>308</idPartType>
      <value>81.29</value>
      <dueDate>23</dueDate>
    </part>
    <part id="308:24">
      <idPartType>308</idPartType>
      <value>66.57</value>
      <dueDate>19</dueDate>
    </part>
    <part id="308:25">
      <idPartType>308</idPartType>
      <value>87.73</value>
      <dueDate>38</dueDate>
    </part>
    <part id="308:26">
      <idPartType>308</idPartType>
      <value>65.46</value>
      <dueDate>55</dueDate>
    </part>
    <part id="308:27">
      <idPartType>308</idPartType>
      <value>21.23</value>
      <dueDate>85</dueDate>
    </part>
    <part id="308:28">
      <idPartType>308</idPartType>
      <value>41.34</value>
      <dueDate>6</dueDate>
    </part>
    <part id="308:29">
      <idPartType>308</idPartType>
      <value>58.85</value>
      <dueDate>76</dueDate>
    </part>
    <part id="308:30">
      <idPartType>308</idPartType>
      <value>95.12</value>
      <dueDate>80</dueDate>
    </part>
    <part id="293:0">
      <idPartType>293</idPartType>
      <value>63.51</value>
      <dueDate>47</dueDate>
    </part>
    <part id="293:1">
      <idPartType>293</idPartType>
      <value>19.11</value>
      <dueDate>11</dueDate>
    </part>
    <part id="293:2">
      <idPartType>293</idPartType>
      <value>27.74</value>
      <dueDate>28</dueDate>
    </part>
    <part id="293:3">
      <idPartType>293</idPartType>
      <value>45.89</value>
      <dueDate>48</dueDate>
    </part>
    <part id="293:4">
      <idPartType>293</idPartType>
      <value>100.7</value>
      <dueDate>18</dueDate>
    </part>
    <part id="293:5">
      <idPartType>293</idPartType>
      <value>98.41</value>
      <dueDate>12</dueDate>
    </part>
    <part id="293:6">
      <idPartType>293</idPartType>
      <value>36.79</value>
      <dueDate>54</dueDate>
    </part>
    <part id="293:7">
      <idPartType>293</idPartType>
      <value>38.68</value>
      <dueDate>22</dueDate>
    </part>
    <part id="293:8">
      <idPartType>293</idPartType>
      <value>60.93</value>
      <dueDate>27</dueDate>
    </part>
    <part id="293:9">
      <idPartType>293</idPartType>
      <value>76.84</value>
      <dueDate>66</dueDate>
    </part>
    <part id="293:10">
      <idPartType>293</idPartType>
      <value>60.06</value>
      <dueDate>52</dueDate>
    </part>
    <part id="293:11">
      <idPartType>293</idPartType>
      <value>40.85</value>
      <dueDate>4</dueDate>
    </part>
    <part id="293:12">
      <idPartType>293</idPartType>
      <value>77.45</value>
      <dueDate>70</dueDate>
    </part>
    <part id="293:13">
      <idPartType>293</idPartType>
      <value>26.61</value>
      <dueDate>80</dueDate>
    </part>
    <part id="293:14">
      <idPartType>293</idPartType>
      <value>55.69</value>
      <dueDate>57</dueDate>
    </part>
    <part id="293:15">
      <idPartType>293</idPartType>
      <value>89.49</value>
      <dueDate>50</dueDate>
    </part>
    <part id="293:16">
      <idPartType>293</idPartType>
      <value>65.96</value>
      <dueDate>19</dueDate>
    </part>
    <part id="293:17">
      <idPartType>293</idPartType>
      <value>8.98</value>
      <dueDate>58</dueDate>
    </part>
    <part id="293:18">
      <idPartType>293</idPartType>
      <value>95.66</value>
      <dueDate>15</dueDate>
    </part>
    <part id="293:19">
      <idPartType>293</idPartType>
      <value>66.9</value>
      <dueDate>11</dueDate>
    </part>
    <part id="293:20">
      <idPartType>293</idPartType>
      <value>39.26</value>
      <dueDate>10</dueDate>
    </part>
    <part id="293:21">
      <idPartType>293</idPartType>
      <value>79.28</value>
      <dueDate>60</dueDate>
    </part>
    <part id="293:22">
      <idPartType>293</idPartType>
      <value>40.17</value>
      <dueDate>63</dueDate>
    </part>
    <part id="293:23">
      <idPartType>293</idPartType>
      <value>30.26</value>
      <dueDate>59</dueDate>
    </part>
    <part id="293:24">
      <idPartType>293</idPartType>
      <value>77.7</value>
      <dueDate>68</dueDate>
    </part>
    <part id="293:25">
      <idPartType>293</idPartType>
      <value>30.77</value>
      <dueDate>71</dueDate>
    </part>
    <part id="293:26">
      <idPartType>293</idPartType>
      <value>4.17</value>
      <dueDate>1</dueDate>
    </part>
    <part id="293:27">
      <idPartType>293</idPartType>
      <value>26.09</value>
      <dueDate>25</dueDate>
    </part>
    <part id="293:28">
      <idPartType>293</idPartType>
      <value>83.43</value>
      <dueDate>50</dueDate>
    </part>
    <part id="293:29">
      <idPartType>293</idPartType>
      <value>74.46</value>
      <dueDate>11</dueDate>
    </part>
    <part id="293:30">
      <idPartType>293</idPartType>
      <value>87.32</value>
      <dueDate>2</dueDate>
    </part>
    <part id="293:31">
      <idPartType>293</idPartType>
      <value>25.23</value>
      <dueDate>70</dueDate>
    </part>
    <part id="293:32">
      <idPartType>293</idPartType>
      <value>42.03</value>
      <dueDate>33</dueDate>
    </part>
    <part id="374:0">
      <idPartType>374</idPartType>
      <value>6.25</value>
      <dueDate>7</dueDate>
    </part>
    <part id="374:1">
      <idPartType>374</idPartType>
      <value>50.67</value>
      <dueDate>76</dueDate>
    </part>
    <part id="374:2">
      <idPartType>374</idPartType>
      <value>13.71</value>
      <dueDate>45</dueDate>
    </part>
    <part id="374:3">
      <idPartType>374</idPartType>
      <value>77.85</value>
      <dueDate>84</dueDate>
    </part>
    <part id="374:4">
      <idPartType>374</idPartType>
      <value>39.0</value>
      <dueDate>67</dueDate>
    </part>
    <part id="374:5">
      <idPartType>374</idPartType>
      <value>49.08</value>
      <dueDate>84</dueDate>
    </part>
    <part id="374:6">
      <idPartType>374</idPartType>
      <value>13.09</value>
      <dueDate>37</dueDate>
    </part>
    <part id="374:7">
      <idPartType>374</idPartType>
      <value>44.26</value>
      <dueDate>31</dueDate>
    </part>
    <part id="374:8">
      <idPartType>374</idPartType>
      <value>75.56</value>
      <dueDate>57</dueDate>
    </part>
    <part id="374:9">
      <idPartType>374</idPartType>
      <value>97.63</value>
      <dueDate>12</dueDate>
    </part>
    <part id="374:10">
      <idPartType>374</idPartType>
      <value>70.15</value>
      <dueDate>18</dueDate>
    </part>
    <part id="374:11">
      <idPartType>374</idPartType>
      <value>28.89</value>
      <dueDate>30</dueDate>
    </part>
    <part id="374:12">
      <idPartType>374</idPartType>
      <value>32.38</value>
      <dueDate>84</dueDate>
    </part>
    <part id="374:13">
      <idPartType>374</idPartType>
      <value>22.26</value>
      <dueDate>2</dueDate>
    </part>
    <part id="374:14">
      <idPartType>374</idPartType>
      <value>16.49</value>
      <dueDate>9</dueDate>
    </part>
    <part id="374:15">
      <idPartType>374</idPartType>
      <value>59.02</value>
      <dueDate>19</dueDate>
    </part>
    <part id="374:16">
      <idPartType>374</idPartType>
      <value>39.67</value>
      <dueDate>6</dueDate>
    </part>
    <part id="374:17">
      <idPartType>374</idPartType>
      <value>34.04</value>
      <dueDate>34</dueDate>
    </part>
    <part id="374:18">
      <idPartType>374</idPartType>
      <value>15.08</value>
      <dueDate>37</dueDate>
    </part>
    <part id="374:19">
      <idPartType>374</idPartType>
      <value>66.67</value>
      <dueDate>18</dueDate>
    </part>
    <part id="374:20">
      <idPartType>374</idPartType>
      <value>2.76</value>
      <dueDate>30</dueDate>
    </part>
    <part id="374:21">
      <idPartType>374</idPartType>
      <value>66.64</value>
      <dueDate>18</dueDate>
    </part>
    <part id="374:22">
      <idPartType>374</idPartType>
      <value>70.53</value>
      <dueDate>14</dueDate>
    </part>
    <part id="374:23">
      <idPartType>374</idPartType>
      <value>57.36</value>
      <dueDate>65</dueDate>
    </part>
    <part id="374:24">
      <idPartType>374</idPartType>
      <value>4.82</value>
      <dueDate>36</dueDate>
    </part>
    <part id="374:25">
      <idPartType>374</idPartType>
      <value>25.66</value>
      <dueDate>18</dueDate>
    </part>
    <part id="374:26">
      <idPartType>374</idPartType>
      <value>17.34</value>
      <dueDate>19</dueDate>
    </part>
    <part id="374:27">
      <idPartType>374</idPartType>
      <value>33.15</value>
      <dueDate>14</dueDate>
    </part>
    <part id="374:28">
      <idPartType>374</idPartType>
      <value>20.09</value>
      <dueDate>64</dueDate>
    </part>
    <part id="374:29">
      <idPartType>374</idPartType>
      <value>46.15</value>
      <dueDate>79</dueDate>
    </part>
    <part id="374:30">
      <idPartType>374</idPartType>
      <value>23.87</value>
      <dueDate>17</dueDate>
    </part>
    <part id="374:31">
      <idPartType>374</idPartType>
      <value>50.64</value>
      <dueDate>69</dueDate>
    </part>
    <part id="374:32">
      <idPartType>374</idPartType>
      <value>29.9</value>
      <dueDate>54</dueDate>
    </part>
    <part id="374:33">
      <idPartType>374</idPartType>
      <value>21.94</value>
      <dueDate>84</dueDate>
    </part>
    <part id="374:34">
      <idPartType>374</idPartType>
      <value>66.01</value>
      <dueDate>8</dueDate>
    </part>
    <part id="374:35">
      <idPartType>374</idPartType>
      <value>68.15</value>
      <dueDate>19</dueDate>
    </part>
    <part id="374:36">
      <idPartType>374</idPartType>
      <value>46.04</value>
      <dueDate>66</dueDate>
    </part>
    <part id="7:0">
      <idPartType>7</idPartType>
      <value>21.48</value>
      <dueDate>40</dueDate>
    </part>
    <part id="7:1">
      <idPartType>7</idPartType>
      <value>64.14</value>
      <dueDate>10</dueDate>
    </part>
    <part id="7:2">
      <idPartType>7</idPartType>
      <value>15.4</value>
      <dueDate>16</dueDate>
    </part>
    <part id="7:3">
      <idPartType>7</idPartType>
      <value>33.12</value>
      <dueDate>58</dueDate>
    </part>
    <part id="7:4">
      <idPartType>7</idPartType>
      <value>6.14</value>
      <dueDate>11</dueDate>
    </part>
    <part id="7:5">
      <idPartType>7</idPartType>
      <value>17.42</value>
      <dueDate>71</dueDate>
    </part>
    <part id="7:6">
      <idPartType>7</idPartType>
      <value>32.2</value>
      <dueDate>67</dueDate>
    </part>
    <part id="7:7">
      <idPartType>7</idPartType>
      <value>36.61</value>
      <dueDate>41</dueDate>
    </part>
    <part id="7:8">
      <idPartType>7</idPartType>
      <value>15.92</value>
      <dueDate>22</dueDate>
    </part>
    <part id="7:9">
      <idPartType>7</idPartType>
      <value>64.6</value>
      <dueDate>85</dueDate>
    </part>
    <part id="7:10">
      <idPartType>7</idPartType>
      <value>91.31</value>
      <dueDate>76</dueDate>
    </part>
    <part id="7:11">
      <idPartType>7</idPartType>
      <value>99.08</value>
      <dueDate>52</dueDate>
    </part>
    <part id="7:12">
      <idPartType>7</idPartType>
      <value>35.04</value>
      <dueDate>42</dueDate>
    </part>
    <part id="7:13">
      <idPartType>7</idPartType>
      <value>98.76</value>
      <dueDate>80</dueDate>
    </part>
    <part id="7:14">
      <idPartType>7</idPartType>
      <value>83.23</value>
      <dueDate>33</dueDate>
    </part>
    <part id="7:15">
      <idPartType>7</idPartType>
      <value>31.71</value>
      <dueDate>54</dueDate>
    </part>
    <part id="7:16">
      <idPartType>7</idPartType>
      <value>28.42</value>
      <dueDate>25</dueDate>
    </part>
    <part id="7:17">
      <idPartType>7</idPartType>
      <value>40.59</value>
      <dueDate>39</dueDate>
    </part>
    <part id="7:18">
      <idPartType>7</idPartType>
      <value>77.84</value>
      <dueDate>48</dueDate>
    </part>
    <part id="7:19">
      <idPartType>7</idPartType>
      <value>84.24</value>
      <dueDate>57</dueDate>
    </part>
    <part id="7:20">
      <idPartType>7</idPartType>
      <value>84.89</value>
      <dueDate>61</dueDate>
    </part>
    <part id="7:21">
      <idPartType>7</idPartType>
      <value>51.73</value>
      <dueDate>42</dueDate>
    </part>
    <part id="7:22">
      <idPartType>7</idPartType>
      <value>36.82</value>
      <dueDate>16</dueDate>
    </part>
    <part id="7:23">
      <idPartType>7</idPartType>
      <value>66.28</value>
      <dueDate>37</dueDate>
    </part>
    <part id="7:24">
      <idPartType>7</idPartType>
      <value>79.68</value>
      <dueDate>78</dueDate>
    </part>
    <part id="7:25">
      <idPartType>7</idPartType>
      <value>43.41</value>
      <dueDate>61</dueDate>
    </part>
    <part id="7:26">
      <idPartType>7</idPartType>
      <value>72.14</value>
      <dueDate>20</dueDate>
    </part>
    <part id="7:27">
      <idPartType>7</idPartType>
      <value>47.12</value>
      <dueDate>4</dueDate>
    </part>
    <part id="7:28">
      <idPartType>7</idPartType>
      <value>98.6</value>
      <dueDate>52</dueDate>
    </part>
    <part id="7:29">
      <idPartType>7</idPartType>
      <value>99.4</value>
      <dueDate>29</dueDate>
    </part>
    <part id="7:30">
      <idPartType>7</idPartType>
      <value>86.78</value>
      <dueDate>35</dueDate>
    </part>
    <part id="7:31">
      <idPartType>7</idPartType>
      <value>39.38</value>
      <dueDate>15</dueDate>
    </part>
    <part id="7:32">
      <idPartType>7</idPartType>
      <value>48.44</value>
      <dueDate>31</dueDate>
    </part>
    <part id="7:33">
      <idPartType>7</idPartType>
      <value>4.5</value>
      <dueDate>29</dueDate>
    </part>
    <part id="7:34">
      <idPartType>7</idPartType>
      <value>92.44</value>
      <dueDate>2</dueDate>
    </part>
    <part id="7:35">
      <idPartType>7</idPartType>
      <value>30.4</value>
      <dueDate>63</dueDate>
    </part>
    <part id="7:36">
      <idPartType>7</idPartType>
      <value>17.95</value>
      <dueDate>85</dueDate>
    </part>
    <part id="7:37">
      <idPartType>7</idPartType>
      <value>16.0</value>
      <dueDate>15</dueDate>
    </part>
    <part id="7:38">
      <idPartType>7</idPartType>
      <value>43.93</value>
      <dueDate>58</dueDate>
    </part>
    <part id="7:39">
      <idPartType>7</idPartType>
      <value>1.76</value>
      <dueDate>7</dueDate>
    </part>
    <part id="7:40">
      <idPartType>7</idPartType>
      <value>85.52</value>
      <dueDate>71</dueDate>
    </part>
    <part id="7:41">
      <idPartType>7</idPartType>
      <value>75.81</value>
      <dueDate>11</dueDate>
    </part>
    <part id="7:42">
      <idPartType>7</idPartType>
      <value>17.32</value>
      <dueDate>83</dueDate>
    </part>
    <part id="7:43">
      <idPartType>7</idPartType>
      <value>94.26</value>
      <dueDate>27</dueDate>
    </part>
    <part id="7:44">
      <idPartType>7</idPartType>
      <value>82.37</value>
      <dueDate>40</dueDate>
    </part>
    <part id="375:0">
      <idPartType>375</idPartType>
      <value>72.97</value>
      <dueDate>43</dueDate>
    </part>
    <part id="375:1">
      <idPartType>375</idPartType>
      <value>66.94</value>
      <dueDate>52</dueDate>
    </part>
    <part id="375:2">
      <idPartType>375</idPartType>
      <value>68.07</value>
      <dueDate>22</dueDate>
    </part>
    <part id="375:3">
      <idPartType>375</idPartType>
      <value>83.27</value>
      <dueDate>55</dueDate>
    </part>
    <part id="375:4">
      <idPartType>375</idPartType>
      <value>91.19</value>
      <dueDate>62</dueDate>
    </part>
    <part id="375:5">
      <idPartType>375</idPartType>
      <value>41.64</value>
      <dueDate>35</dueDate>
    </part>
    <part id="375:6">
      <idPartType>375</idPartType>
      <value>44.36</value>
      <dueDate>11</dueDate>
    </part>
    <part id="375:7">
      <idPartType>375</idPartType>
      <value>82.6</value>
      <dueDate>42</dueDate>
    </part>
    <part id="375:8">
      <idPartType>375</idPartType>
      <value>24.71</value>
      <dueDate>23</dueDate>
    </part>
    <part id="375:9">
      <idPartType>375</idPartType>
      <value>8.94</value>
      <dueDate>20</dueDate>
    </part>
    <part id="375:10">
      <idPartType>375</idPartType>
      <value>27.74</value>
      <dueDate>12</dueDate>
    </part>
    <part id="375:11">
      <idPartType>375</idPartType>
      <value>27.2</value>
      <dueDate>9</dueDate>
    </part>
    <part id="375:12">
      <idPartType>375</idPartType>
      <value>100.13</value>
      <dueDate>14</dueDate>
    </part>
    <part id="375:13">
      <idPartType>375</idPartType>
      <value>4.52</value>
      <dueDate>20</dueDate>
    </part>
    <part id="375:14">
      <idPartType>375</idPartType>
      <value>14.55</value>
      <dueDate>15</dueDate>
    </part>
    <part id="375:15">
      <idPartType>375</idPartType>
      <value>74.56</value>
      <dueDate>69</dueDate>
    </part>
    <part id="375:16">
      <idPartType>375</idPartType>
      <value>84.79</value>
      <dueDate>82</dueDate>
    </part>
    <part id="375:17">
      <idPartType>375</idPartType>
      <value>88.37</value>
      <dueDate>20</dueDate>
    </part>
    <part id="375:18">
      <idPartType>375</idPartType>
      <value>17.93</value>
      <dueDate>84</dueDate>
    </part>
    <part id="375:19">
      <idPartType>375</idPartType>
      <value>65.47</value>
      <dueDate>37</dueDate>
    </part>
    <part id="375:20">
      <idPartType>375</idPartType>
      <value>98.39</value>
      <dueDate>77</dueDate>
    </part>
    <part id="375:21">
      <idPartType>375</idPartType>
      <value>84.24</value>
      <dueDate>56</dueDate>
    </part>
    <part id="375:22">
      <idPartType>375</idPartType>
      <value>51.6</value>
      <dueDate>4</dueDate>
    </part>
    <part id="375:23">
      <idPartType>375</idPartType>
      <value>84.11</value>
      <dueDate>6</dueDate>
    </part>
    <part id="375:24">
      <idPartType>375</idPartType>
      <value>27.53</value>
      <dueDate>9</dueDate>
    </part>
    <part id="375:25">
      <idPartType>375</idPartType>
      <value>11.1</value>
      <dueDate>58</dueDate>
    </part>
    <part id="375:26">
      <idPartType>375</idPartType>
      <value>33.44</value>
      <dueDate>64</dueDate>
    </part>
    <part id="375:27">
      <idPartType>375</idPartType>
      <value>99.87</value>
      <dueDate>34</dueDate>
    </part>
    <part id="375:28">
      <idPartType>375</idPartType>
      <value>99.81</value>
      <dueDate>84</dueDate>
    </part>
    <part id="375:29">
      <idPartType>375</idPartType>
      <value>78.09</value>
      <dueDate>60</dueDate>
    </part>
    <part id="375:30">
      <idPartType>375</idPartType>
      <value>9.82</value>
      <dueDate>77</dueDate>
    </part>
    <part id="375:31">
      <idPartType>375</idPartType>
      <value>69.18</value>
      <dueDate>7</dueDate>
    </part>
    <part id="375:32">
      <idPartType>375</idPartType>
      <value>30.67</value>
      <dueDate>6</dueDate>
    </part>
    <part id="375:33">
      <idPartType>375</idPartType>
      <value>24.24</value>
      <dueDate>66</dueDate>
    </part>
    <part id="375:34">
      <idPartType>375</idPartType>
      <value>81.88</value>
      <dueDate>61</dueDate>
    </part>
    <part id="375:35">
      <idPartType>375</idPartType>
      <value>29.28</value>
      <dueDate>71</dueDate>
    </part>
    <part id="189:0">
      <idPartType>189</idPartType>
      <value>60.81</value>
      <dueDate>27</dueDate>
    </part>
    <part id="189:1">
      <idPartType>189</idPartType>
      <value>93.47</value>
      <dueDate>45</dueDate>
    </part>
    <part id="189:2">
      <idPartType>189</idPartType>
      <value>94.75</value>
      <dueDate>34</dueDate>
    </part>
    <part id="189:3">
      <idPartType>189</idPartType>
      <value>49.81</value>
      <dueDate>18</dueDate>
    </part>
    <part id="189:4">
      <idPartType>189</idPartType>
      <value>52.82</value>
      <dueDate>82</dueDate>
    </part>
    <part id="189:5">
      <idPartType>189</idPartType>
      <value>69.66</value>
      <dueDate>56</dueDate>
    </part>
    <part id="189:6">
      <idPartType>189</idPartType>
      <value>47.34</value>
      <dueDate>80</dueDate>
    </part>
    <part id="189:7">
      <idPartType>189</idPartType>
      <value>63.74</value>
      <dueDate>63</dueDate>
    </part>
    <part id="189:8">
      <idPartType>189</idPartType>
      <value>82.56</value>
      <dueDate>76</dueDate>
    </part>
    <part id="189:9">
      <idPartType>189</idPartType>
      <value>68.58</value>
      <dueDate>8</dueDate>
    </part>
    <part id="189:10">
      <idPartType>189</idPartType>
      <value>98.78</value>
      <dueDate>42</dueDate>
    </part>
    <part id="189:11">
      <idPartType>189</idPartType>
      <value>71.12</value>
      <dueDate>55</dueDate>
    </part>
    <part id="189:12">
      <idPartType>189</idPartType>
      <value>13.89</value>
      <dueDate>3</dueDate>
    </part>
    <part id="189:13">
      <idPartType>189</idPartType>
      <value>27.05</value>
      <dueDate>10</dueDate>
    </part>
    <part id="189:14">
      <idPartType>189</idPartType>
      <value>3.08</value>
      <dueDate>28</dueDate>
    </part>
    <part id="189:15">
      <idPartType>189</idPartType>
      <value>72.9</value>
      <dueDate>82</dueDate>
    </part>
    <part id="189:16">
      <idPartType>189</idPartType>
      <value>76.66</value>
      <dueDate>50</dueDate>
    </part>
    <part id="189:17">
      <idPartType>189</idPartType>
      <value>17.71</value>
      <dueDate>23</dueDate>
    </part>
    <part id="189:18">
      <idPartType>189</idPartType>
      <value>47.28</value>
      <dueDate>19</dueDate>
    </part>
    <part id="189:19">
      <idPartType>189</idPartType>
      <value>27.41</value>
      <dueDate>23</dueDate>
    </part>
    <part id="189:20">
      <idPartType>189</idPartType>
      <value>18.64</value>
      <dueDate>3</dueDate>
    </part>
    <part id="189:21">
      <idPartType>189</idPartType>
      <value>93.01</value>
      <dueDate>8</dueDate>
    </part>
    <part id="189:22">
      <idPartType>189</idPartType>
      <value>12.59</value>
      <dueDate>45</dueDate>
    </part>
    <part id="189:23">
      <idPartType>189</idPartType>
      <value>38.85</value>
      <dueDate>74</dueDate>
    </part>
    <part id="189:24">
      <idPartType>189</idPartType>
      <value>87.64</value>
      <dueDate>78</dueDate>
    </part>
    <part id="189:25">
      <idPartType>189</idPartType>
      <value>57.41</value>
      <dueDate>52</dueDate>
    </part>
    <part id="189:26">
      <idPartType>189</idPartType>
      <value>20.83</value>
      <dueDate>81</dueDate>
    </part>
    <part id="189:27">
      <idPartType>189</idPartType>
      <value>48.15</value>
      <dueDate>74</dueDate>
    </part>
    <part id="189:28">
      <idPartType>189</idPartType>
      <value>31.47</value>
      <dueDate>17</dueDate>
    </part>
    <part id="189:29">
      <idPartType>189</idPartType>
      <value>32.99</value>
      <dueDate>29</dueDate>
    </part>
    <part id="189:30">
      <idPartType>189</idPartType>
      <value>79.07</value>
      <dueDate>61</dueDate>
    </part>
    <part id="189:31">
      <idPartType>189</idPartType>
      <value>47.7</value>
      <dueDate>74</dueDate>
    </part>
    <part id="189:32">
      <idPartType>189</idPartType>
      <value>19.91</value>
      <dueDate>48</dueDate>
    </part>
    <part id="189:33">
      <idPartType>189</idPartType>
      <value>14.93</value>
      <dueDate>2</dueDate>
    </part>
    <part id="189:34">
      <idPartType>189</idPartType>
      <value>38.62</value>
      <dueDate>18</dueDate>
    </part>
    <part id="189:35">
      <idPartType>189</idPartType>
      <value>29.3</value>
      <dueDate>35</dueDate>
    </part>
    <part id="189:36">
      <idPartType>189</idPartType>
      <value>76.35</value>
      <dueDate>37</dueDate>
    </part>
    <part id="189:37">
      <idPartType>189</idPartType>
      <value>68.33</value>
      <dueDate>50</dueDate>
    </part>
    <part id="189:38">
      <idPartType>189</idPartType>
      <value>46.35</value>
      <dueDate>11</dueDate>
    </part>
    <part id="93:0">
      <idPartType>93</idPartType>
      <value>78.91</value>
      <dueDate>44</dueDate>
    </part>
    <part id="93:1">
      <idPartType>93</idPartType>
      <value>18.02</value>
      <dueDate>44</dueDate>
    </part>
    <part id="93:2">
      <idPartType>93</idPartType>
      <value>50.25</value>
      <dueDate>83</dueDate>
    </part>
    <part id="93:3">
      <idPartType>93</idPartType>
      <value>79.23</value>
      <dueDate>57</dueDate>
    </part>
    <part id="93:4">
      <idPartType>93</idPartType>
      <value>84.19</value>
      <dueDate>81</dueDate>
    </part>
    <part id="93:5">
      <idPartType>93</idPartType>
      <value>97.66</value>
      <dueDate>24</dueDate>
    </part>
    <part id="93:6">
      <idPartType>93</idPartType>
      <value>19.95</value>
      <dueDate>27</dueDate>
    </part>
    <part id="93:7">
      <idPartType>93</idPartType>
      <value>18.4</value>
      <dueDate>45</dueDate>
    </part>
    <part id="93:8">
      <idPartType>93</idPartType>
      <value>35.02</value>
      <dueDate>31</dueDate>
    </part>
    <part id="93:9">
      <idPartType>93</idPartType>
      <value>97.58</value>
      <dueDate>31</dueDate>
    </part>
    <part id="93:10">
      <idPartType>93</idPartType>
      <value>37.23</value>
      <dueDate>82</dueDate>
    </part>
    <part id="93:11">
      <idPartType>93</idPartType>
      <value>77.72</value>
      <dueDate>20</dueDate>
    </part>
    <part id="93:12">
      <idPartType>93</idPartType>
      <value>89.68</value>
      <dueDate>55</dueDate>
    </part>
    <part id="93:13">
      <idPartType>93</idPartType>
      <value>77.08</value>
      <dueDate>11</dueDate>
    </part>
    <part id="93:14">
      <idPartType>93</idPartType>
      <value>24.11</value>
      <dueDate>41</dueDate>
    </part>
    <part id="93:15">
      <idPartType>93</idPartType>
      <value>51.43</value>
      <dueDate>55</dueDate>
    </part>
    <part id="93:16">
      <idPartType>93</idPartType>
      <value>97.36</value>
      <dueDate>22</dueDate>
    </part>
    <part id="93:17">
      <idPartType>93</idPartType>
      <value>18.63</value>
      <dueDate>5</dueDate>
    </part>
    <part id="93:18">
      <idPartType>93</idPartType>
      <value>47.83</value>
      <dueDate>24</dueDate>
    </part>
    <part id="93:19">
      <idPartType>93</idPartType>
      <value>73.2</value>
      <dueDate>76</dueDate>
    </part>
    <part id="93:20">
      <idPartType>93</idPartType>
      <value>13.23</value>
      <dueDate>50</dueDate>
    </part>
    <part id="93:21">
      <idPartType>93</idPartType>
      <value>57.28</value>
      <dueDate>60</dueDate>
    </part>
    <part id="93:22">
      <idPartType>93</idPartType>
      <value>63.98</value>
      <dueDate>43</dueDate>
    </part>
    <part id="93:23">
      <idPartType>93</idPartType>
      <value>80.62</value>
      <dueDate>47</dueDate>
    </part>
    <part id="93:24">
      <idPartType>93</idPartType>
      <value>95.96</value>
      <dueDate>13</dueDate>
    </part>
    <part id="93:25">
      <idPartType>93</idPartType>
      <value>35.73</value>
      <dueDate>63</dueDate>
    </part>
    <part id="93:26">
      <idPartType>93</idPartType>
      <value>66.33</value>
      <dueDate>67</dueDate>
    </part>
    <part id="93:27">
      <idPartType>93</idPartType>
      <value>87.38</value>
      <dueDate>74</dueDate>
    </part>
    <part id="93:28">
      <idPartType>93</idPartType>
      <value>26.24</value>
      <dueDate>31</dueDate>
    </part>
    <part id="93:29">
      <idPartType>93</idPartType>
      <value>76.39</value>
      <dueDate>37</dueDate>
    </part>
    <part id="93:30">
      <idPartType>93</idPartType>
      <value>23.09</value>
      <dueDate>68</dueDate>
    </part>
    <part id="93:31">
      <idPartType>93</idPartType>
      <value>73.67</value>
      <dueDate>33</dueDate>
    </part>
  </parts>
</problemDefinition>